{"Dialogue":"Film it! Are you \u2013 sing it, Karl. Con \u2013 film him, film this.","Sentiment":"neutral","Score":0.6826192737}
{"Dialogue":"\u2026 Gore, Dole, Bush, Mike D.,","Sentiment":"neutral","Score":0.8685048819}
{"Dialogue":"Mondale, Carter, A. Ford not a Lincoln for me,","Sentiment":"neutral","Score":0.6347379088}
{"Dialogue":"Hippy George, Humphrey, St Barry, Dick the Bad, Stephenson,","Sentiment":"neutral","Score":0.7722492814}
{"Dialogue":"Dewey so saddy,","Sentiment":"neutral","Score":0.5806714296}
{"Dialogue":"Wilkie, Landon, Hoover, Al Smith of the Vatican,","Sentiment":"neutral","Score":0.9240605831}
{"Dialogue":"Davis, Cox, Hughes, Taft, Bryan try that again,","Sentiment":"neutral","Score":0.8535499573}
{"Dialogue":"Parker, Bryan once more, Harrison, Cleveland, Blaine,","Sentiment":"neutral","Score":0.8222149611}
{"Dialogue":"Hancock, and more,","Sentiment":"neutral","Score":0.8232963681}
{"Dialogue":"Tilden, Greeley, Seymour,","Sentiment":"neutral","Score":0.902254343}
{"Dialogue":"George B. McClellan, in the union\u2019s blue,","Sentiment":"neutral","Score":0.8456349373}
{"Dialogue":"Stephen A. Douglas he lost too. Fremont, Scott, Cass and Clay,","Sentiment":"neutral","Score":0.54091084}
{"Dialogue":"heroes of their day but all went away,","Sentiment":"neutral","Score":0.5041726232}
{"Dialogue":"Martin Van Buren, White, and Old Tippecanoe,","Sentiment":"neutral","Score":0.9260869026}
{"Dialogue":"Clay, hey ","Sentiment":"neutral","Score":0.8180015087}
{"Dialogue":"Not very nice, Gerri, not very nice. Do the \u2013 do the limerick!","Sentiment":"negative","Score":0.9367107153}
{"Dialogue":"Connor?","Sentiment":"neutral","Score":0.8984391689}
{"Dialogue":"Great stuff. Very good.","Sentiment":"positive","Score":0.9855496287}
{"Dialogue":"Say, is there a game on?","Sentiment":"neutral","Score":0.9362184405}
{"Dialogue":"Karl. Come on. Sing it.","Sentiment":"neutral","Score":0.5430924296}
{"Dialogue":"Film him. I want a copy of this. I\u2019d like to have it with me always","Sentiment":"positive","Score":0.9119790792}
{"Dialogue":"\u2014","Sentiment":"neutral","Score":0.5303393602}
{"Dialogue":"in case I go fucking rat-catching. Go on. Karl! Sing it!","Sentiment":"negative","Score":0.6390613317}
{"Dialogue":"You\u2019re fucking murdering it, man.","Sentiment":"negative","Score":0.9394806623}
{"Dialogue":"Kerry! Listen, he\u2019s murdering it. He\u2019s killing it!","Sentiment":"negative","Score":0.6843881607}
